tastyworks/__init__.py
tastyworks/streamer.py
tastyworks/utils.py
tastyworks/dough/__init__.py
tastyworks/dough/stocks.py
tastyworks/dxfeed/__init__.py
tastyworks/dxfeed/greeks.py
tastyworks/dxfeed/mapped_item.py
tastyworks/dxfeed/mapper.py
tastyworks/dxfeed/profile.py
tastyworks/dxfeed/quote.py
tastyworks/dxfeed/summary.py
tastyworks/dxfeed/trade.py
tastyworks/models/__init__.py
tastyworks/models/greeks.py
tastyworks/models/option.py
tastyworks/models/option_chain.py
tastyworks/models/order.py
tastyworks/models/security.py
tastyworks/models/session.py
tastyworks/models/trading_account.py
tastyworks/models/underlying.py
tastyworks/models/watchlists.py
tastyworks/tastyworks_api/__init__.py
tastyworks/tastyworks_api/symbol_search.py
tastyworks/tastyworks_api/symbols.py
tastyworks/tastyworks_api/tasty_session.py
tastyworks_api-4.3.0.dist-info/LICENSE.txt
tastyworks_api-4.3.0.dist-info/METADATA
tastyworks_api-4.3.0.dist-info/WHEEL
tastyworks_api-4.3.0.dist-info/top_level.txt
tastyworks_api-4.3.0.dist-info/RECORD
