Metadata-Version: 2.1
Name: tastyworks-api
Version: 4.3.0
Summary: An unofficial API for Tastyworks!
Home-page: https://github.com/tastyware/tastyworks-api
Author: Graeme Holliday
Author-email: graeme.holliday@pm.me
License: Apache
Platform: UNKNOWN
License-File: LICENSE.txt
Requires-Dist: aiohttp (<4)
Requires-Dist: requests (<3)
Requires-Dist: tastyworks-aiocometd (>=1.0)
Requires-Dist: dataclasses
